README.rst
setup.py
foscam/__init__.py
foscam/foscam.py
pyfoscam.egg-info/PKG-INFO
pyfoscam.egg-info/SOURCES.txt
pyfoscam.egg-info/dependency_links.txt
pyfoscam.egg-info/not-zip-safe
pyfoscam.egg-info/top_level.txt