Metadata-Version: 1.0
Name: pyfoscam
Version: 1.2
Summary: Foscam Python Library for H.264 IP Cameras (FI9821W/P/HD816W/P)
Home-page: https://github.com/quatanium/foscam-python-lib
Author: Cherish Chen
Author-email: sinchb128@gmail.com
License: MIT
Keywords: foscam,Camera,IPC
Platform: UNKNOWN
